gem_opt/__init__.py
gem_opt/const.py
gem_opt/main.py
gem_opt/tests/test_graph_utils.py
gem_opt/tests/test_metric_utils.py
gem_opt/tests/test_wrappers/test_scipy.py
gem_opt/utils/__init__.py
gem_opt/utils/graph_utils.py
gem_opt/utils/metric_utils.py
gem_opt/wrappers/__init__.py
gem_opt/wrappers/base.py
gem_opt/wrappers/scipy.py
gem_opt-0.1.1.dist-info/LICENSE
gem_opt-0.1.1.dist-info/METADATA
gem_opt-0.1.1.dist-info/WHEEL
gem_opt-0.1.1.dist-info/RECORD
