Metadata-Version: 2.1
Name: gem-opt
Version: 0.1.1
Summary: Graph-Based Equilibrium Metric Optimization for Dynamic Supply-Demand Systems with Applications to Ride-sourcing Platforms, implemented in Python
Home-page: https://github.com/fred-navruzov/gem-opt
License: MIT
Keywords: optimization,graphs,ride-hailing
Author: Fedir Navruzov
Author-email: fred.navruzov@gmail.com
Requires-Python: >=3.9,<3.12
Classifier: Development Status :: 3 - Alpha
Classifier: Intended Audience :: Science/Research
Classifier: License :: OSI Approved :: MIT License
Classifier: Operating System :: OS Independent
Classifier: Programming Language :: Python
Classifier: Programming Language :: Python :: 3
Classifier: Programming Language :: Python :: 3.9
Classifier: Programming Language :: Python :: 3.10
Classifier: Programming Language :: Python :: 3.11
Classifier: Programming Language :: Python :: 3
Classifier: Programming Language :: Python :: 3 :: Only
Classifier: Programming Language :: Python :: 3.10
Classifier: Programming Language :: Python :: 3.11
Classifier: Programming Language :: Python :: 3.9
Classifier: Programming Language :: Python :: Implementation :: CPython
Classifier: Topic :: Scientific/Engineering
Requires-Dist: networkx (>=3.1,<4.0)
Requires-Dist: numpy (>=1.24.2,<2.0.0)
Requires-Dist: pandas (>=2.0.0,<3.0.0)
Requires-Dist: scipy (>=1.10.1,<2.0.0)
Project-URL: Repository, https://github.com/fred-navruzov/gem-opt
